grandalf/__init__.py
grandalf/graphs.py
grandalf/layouts.py
grandalf/routing.py
grandalf/utils/__init__.py
grandalf/utils/dot.py
grandalf/utils/geometry.py
grandalf/utils/linalg.py
grandalf/utils/nx.py
grandalf/utils/poset.py
grandalf-0.8.dist-info/LICENSE
grandalf-0.8.dist-info/METADATA
grandalf-0.8.dist-info/WHEEL
grandalf-0.8.dist-info/top_level.txt
grandalf-0.8.dist-info/RECORD
