Metadata-Version: 2.1
Name: grandalf
Version: 0.8
Summary: Graph and drawing algorithms framework
Home-page: https://github.com/bdcht/grandalf
Author: Axel Tillequin
Author-email: bdcht3@gmail.com
License: GPLv2 | EPLv1
Keywords: graph drawings graphviz networkx
Platform: UNKNOWN
Classifier: Development Status :: 3 - Alpha
Classifier: Intended Audience :: Developers
Classifier: License :: OSI Approved :: GNU General Public License v2 (GPLv2)
Classifier: Programming Language :: Python :: 3
Provides-Extra: full
